brainfk/__init__.py
brainfk/interpreter.py
brainfk-1.0.0.dist-info/METADATA
brainfk-1.0.0.dist-info/WHEEL
brainfk-1.0.0.dist-info/entry_points.txt
brainfk-1.0.0.dist-info/top_level.txt
brainfk-1.0.0.dist-info/RECORD
