Metadata-Version: 2.1
Name: brainfk
Version: 1.0.0
Summary: A Brainfuck interpreter package
Home-page: https://github.com/estif0/brainfk
Author: Estifanose Sahilu
Requires-Dist: argparse
